mushu/__init__.py
mushu/cli.py
mushu/config.py
mushu/commands/__init__.py
mushu/commands/api_key.py
mushu/commands/app.py
mushu/commands/auth.py
mushu/commands/device.py
mushu/commands/email.py
mushu/commands/media.py
mushu/commands/org.py
mushu/commands/pay.py
mushu/commands/push.py
mushu/commands/tenant.py
mushu_cli-0.1.4.dist-info/METADATA
mushu_cli-0.1.4.dist-info/WHEEL
mushu_cli-0.1.4.dist-info/entry_points.txt
mushu_cli-0.1.4.dist-info/RECORD
