Metadata-Version: 2.4
Name: mushu-cli
Version: 0.1.4
Summary: CLI for Mushu platform (auth + notifications)
Requires-Python: >=3.11
Requires-Dist: httpx>=0.26.0
Requires-Dist: pyjwt>=2.8.0
Requires-Dist: rich>=13.7.0
Requires-Dist: typer>=0.9.0
Provides-Extra: dev
Requires-Dist: pytest>=7.4.0; extra == 'dev'
